{
    "ID": 24651,
    "post_author": "7",
    "post_date": "2022-08-02 07:06:47",
    "post_date_gmt": "2022-08-02 05:06:47",
    "post_content": "",
    "post_title": "Bootstrap Settings",
    "post_excerpt": "",
    "post_status": "publish",
    "comment_status": "closed",
    "ping_status": "closed",
    "post_password": "",
    "post_name": "bstg_settingfields_colors",
    "to_ping": "",
    "pinged": "",
    "post_modified": "2022-08-04 16:34:47",
    "post_modified_gmt": "2022-08-04 14:34:47",
    "post_content_filtered": "",
    "post_parent": 0,
    "guid": "http://verkehr.local/?post_type=meta-box&#038;p=24651",
    "menu_order": 0,
    "post_type": "meta-box",
    "post_mime_type": "",
    "comment_count": "0",
    "filter": "raw",
    "settings": {
        "object_type": "setting",
        "settings_pages": [
            "bstg_general_settings"
        ],
        "tab_style": "default",
        "tab_default_active": "",
        "class": "bstg_settings",
        "prefix": "",
        "text_domain": "hp",
        "function_name": "hp_register_settingColors"
    },
    "fields": {
        "group_jgodo1pe6q": {
            "_id": "group_jgodo1pe6q",
            "_state": "collapsed",
            "name": "",
            "id": "general_settings",
            "type": "group",
            "label_description": "",
            "desc": "",
            "collapsible": true,
            "default_state": "collapsed",
            "save_state": true,
            "group_title": "General Settings",
            "max_clone": "",
            "add_button": "",
            "admin_columns": {
                "position": {
                    "type": "after",
                    "column": "title"
                },
                "title": "",
                "before": "",
                "after": ""
            },
            "columns": 12,
            "tooltip": {
                "icon": "",
                "position": "top",
                "content": ""
            },
            "before": "",
            "after": "",
            "class": "bstg_accordion_wrapper",
            "save_field": true,
            "sanitize_callback": "",
            "fields": {
                "switch_u2mo2c52k1i": {
                    "_id": "switch_u2mo2c52k1i",
                    "_state": "collapsed",
                    "name": "Enqueue Bootstrap inside of Gutenberg?",
                    "id": "enqueue_bs_in_gb",
                    "type": "switch",
                    "label_description": "",
                    "desc": "",
                    "style": "rounded",
                    "on_label": "",
                    "off_label": "",
                    "std": true,
                    "max_clone": "",
                    "add_button": "",
                    "admin_columns": {
                        "position": {
                            "type": "after",
                            "column": "title"
                        },
                        "title": "",
                        "before": "",
                        "after": ""
                    },
                    "columns": 12,
                    "tooltip": {
                        "icon": "",
                        "position": "top",
                        "content": ""
                    },
                    "before": "",
                    "after": "",
                    "class": "",
                    "sanitize_callback": "",
                    "save_field": true
                },
                "switch_9njnl1cok1": {
                    "_id": "switch_9njnl1cok1",
                    "_state": "collapsed",
                    "name": "Where to enqueue Bootstraps' Javascript File",
                    "id": "enqueue_bs_js",
                    "type": "select_advanced",
                    "label_description": "",
                    "desc": "",
                    "options": "backend : Gutenberg\r\nfrontend : Frontend",
                    "std": "",
                    "placeholder": "",
                    "multiple": true,
                    "select_all_none": true,
                    "max_clone": "",
                    "add_button": "",
                    "admin_columns": {
                        "position": {
                            "type": "after",
                            "column": "title"
                        },
                        "title": "",
                        "before": "",
                        "after": ""
                    },
                    "columns": 12,
                    "tooltip": {
                        "enable": true,
                        "icon": "",
                        "position": "top",
                        "content": "bootstrap.min.js"
                    },
                    "before": "",
                    "after": "",
                    "class": "",
                    "sanitize_callback": "",
                    "save_field": true
                }
            }
        },
        "group_p6cv4jokbkq": {
            "_id": "group_p6cv4jokbkq",
            "_state": "collapsed",
            "name": "",
            "id": "components",
            "type": "group",
            "label_description": "",
            "desc": "",
            "collapsible": true,
            "default_state": "collapsed",
            "save_state": true,
            "group_title": "Components",
            "max_clone": "",
            "add_button": "",
            "admin_columns": {
                "position": {
                    "type": "after",
                    "column": "title"
                },
                "title": "",
                "before": "",
                "after": ""
            },
            "columns": 12,
            "tooltip": {
                "icon": "",
                "position": "top",
                "content": ""
            },
            "before": "",
            "after": "",
            "class": "bstg_accordion_wrapper",
            "save_field": true,
            "sanitize_callback": "",
            "fields": {
                "checkbox_xug7ure9v29": {
                    "_id": "checkbox_xug7ure9v29",
                    "_state": "expanded",
                    "name": "Layout",
                    "id": "layout",
                    "type": "checkbox_list",
                    "label_description": "",
                    "desc": "",
                    "options": "callback: components_layout",
                    "std": "",
                    "inline": true,
                    "select_all_none": true,
                    "max_clone": "",
                    "add_button": "",
                    "admin_columns": {
                        "position": {
                            "type": "after",
                            "column": "title"
                        },
                        "title": "",
                        "before": "",
                        "after": ""
                    },
                    "columns": 12,
                    "tooltip": {
                        "icon": "",
                        "position": "top",
                        "content": ""
                    },
                    "before": "",
                    "after": "",
                    "class": "",
                    "sanitize_callback": "",
                    "save_field": true
                },
                "checkbox_list_dv483pkroym": {
                    "_id": "checkbox_list_dv483pkroym",
                    "_state": "expanded",
                    "name": "Design",
                    "id": "design",
                    "type": "checkbox_list",
                    "label_description": "",
                    "desc": "",
                    "options": "callback: components_design",
                    "std": "",
                    "inline": true,
                    "select_all_none": true,
                    "max_clone": "",
                    "add_button": "",
                    "admin_columns": {
                        "position": {
                            "type": "after",
                            "column": "title"
                        },
                        "title": "",
                        "before": "",
                        "after": ""
                    },
                    "columns": 12,
                    "tooltip": {
                        "icon": "",
                        "position": "top",
                        "content": ""
                    },
                    "before": "",
                    "after": "",
                    "class": "",
                    "sanitize_callback": "",
                    "save_field": true
                },
                "checkbox_list_q65yefj6mg": {
                    "_id": "checkbox_list_q65yefj6mg",
                    "_state": "expanded",
                    "name": "Functionality",
                    "id": "functionality",
                    "type": "checkbox_list",
                    "label_description": "",
                    "desc": "",
                    "options": "callback: components_functionality",
                    "std": "",
                    "inline": true,
                    "select_all_none": true,
                    "max_clone": "",
                    "add_button": "",
                    "admin_columns": {
                        "position": {
                            "type": "after",
                            "column": "title"
                        },
                        "title": "",
                        "before": "",
                        "after": ""
                    },
                    "columns": 12,
                    "tooltip": {
                        "icon": "",
                        "position": "top",
                        "content": ""
                    },
                    "before": "",
                    "after": "",
                    "class": "",
                    "sanitize_callback": "",
                    "save_field": true
                }
            }
        },
        "group_sdfpw1rlzop": {
            "_id": "group_sdfpw1rlzop",
            "_state": "expanded",
            "name": "",
            "id": "colors",
            "type": "group",
            "label_description": "",
            "desc": "",
            "collapsible": true,
            "default_state": "collapsed",
            "save_state": true,
            "group_title": "Colors",
            "max_clone": "",
            "add_button": "",
            "admin_columns": {
                "position": {
                    "type": "after",
                    "column": "title"
                },
                "title": "",
                "before": "",
                "after": ""
            },
            "columns": 12,
            "tooltip": {
                "icon": "",
                "position": "top",
                "content": ""
            },
            "before": "",
            "after": "",
            "class": "bstg_accordion_wrapper",
            "save_field": true,
            "sanitize_callback": "",
            "fields": {
                "group_q0efzxp7vjk": {
                    "_id": "group_q0efzxp7vjk",
                    "_state": "collapsed",
                    "name": "Primary",
                    "id": "primary",
                    "type": "color",
                    "label_description": "",
                    "desc": "",
                    "std": "#3f00b5",
                    "alpha_channel": true,
                    "max_clone": "",
                    "add_button": "",
                    "admin_columns": {
                        "position": {
                            "type": "after",
                            "column": "title"
                        },
                        "title": "",
                        "before": "",
                        "after": ""
                    },
                    "columns": 2,
                    "tooltip": {
                        "icon": "",
                        "position": "top",
                        "content": ""
                    },
                    "before": "",
                    "after": "",
                    "class": "",
                    "sanitize_callback": "",
                    "save_field": true
                },
                "group_esqxhqjj757": {
                    "_id": "group_esqxhqjj757",
                    "_state": "collapsed",
                    "name": "Secondary",
                    "id": "secondary",
                    "type": "color",
                    "label_description": "",
                    "desc": "",
                    "std": "#1f1f25",
                    "alpha_channel": true,
                    "max_clone": "",
                    "add_button": "",
                    "admin_columns": {
                        "position": {
                            "type": "after",
                            "column": "title"
                        },
                        "title": "",
                        "before": "",
                        "after": ""
                    },
                    "columns": 2,
                    "tooltip": {
                        "icon": "",
                        "position": "top",
                        "content": ""
                    },
                    "before": "",
                    "after": "",
                    "class": "",
                    "sanitize_callback": "",
                    "save_field": true
                },
                "color_xhqd579c15m": {
                    "_id": "color_xhqd579c15m",
                    "_state": "collapsed",
                    "name": "White",
                    "id": "white",
                    "type": "color",
                    "label_description": "",
                    "desc": "",
                    "std": "#FFFFFF",
                    "max_clone": "",
                    "add_button": "",
                    "admin_columns": {
                        "position": {
                            "type": "after",
                            "column": "title"
                        },
                        "title": "",
                        "before": "",
                        "after": ""
                    },
                    "columns": 2,
                    "tooltip": {
                        "enable": true,
                        "icon": "",
                        "position": "top",
                        "content": "Hauptsächlich für Texte auf dunkleren Hintergründen verwendet!"
                    },
                    "before": "",
                    "after": "",
                    "class": "",
                    "sanitize_callback": "",
                    "save_field": true
                },
                "color_fcx9opg21z": {
                    "_id": "color_fcx9opg21z",
                    "_state": "collapsed",
                    "name": "Light",
                    "id": "light",
                    "type": "color",
                    "label_description": "",
                    "desc": "",
                    "std": "#f8f9fa",
                    "alpha_channel": true,
                    "max_clone": "",
                    "add_button": "",
                    "admin_columns": {
                        "position": {
                            "type": "after",
                            "column": "title"
                        },
                        "title": "",
                        "before": "",
                        "after": ""
                    },
                    "columns": 2,
                    "tooltip": {
                        "enable": true,
                        "icon": "",
                        "position": "top",
                        "content": "Wird beispielsweise für hellere Hintergründe verwendet!"
                    },
                    "before": "",
                    "after": "",
                    "class": "",
                    "sanitize_callback": "",
                    "save_field": true
                },
                "color_r3nkovxp2ie": {
                    "_id": "color_r3nkovxp2ie",
                    "_state": "collapsed",
                    "name": "Dark",
                    "id": "dark",
                    "type": "color",
                    "label_description": "",
                    "desc": "",
                    "std": "#343a40",
                    "alpha_channel": true,
                    "max_clone": "",
                    "add_button": "",
                    "admin_columns": {
                        "position": {
                            "type": "after",
                            "column": "title"
                        },
                        "title": "",
                        "before": "",
                        "after": ""
                    },
                    "columns": 2,
                    "tooltip": {
                        "icon": "",
                        "position": "top",
                        "content": ""
                    },
                    "before": "",
                    "after": "",
                    "class": "",
                    "sanitize_callback": "",
                    "save_field": true
                },
                "color_foy1clj9fqu": {
                    "_id": "color_foy1clj9fqu",
                    "_state": "collapsed",
                    "name": "Warning",
                    "id": "warning",
                    "type": "color",
                    "label_description": "",
                    "desc": "",
                    "std": "#ffc107",
                    "alpha_channel": true,
                    "max_clone": "",
                    "add_button": "",
                    "admin_columns": {
                        "position": {
                            "type": "after",
                            "column": "title"
                        },
                        "title": "",
                        "before": "",
                        "after": ""
                    },
                    "columns": 2,
                    "tooltip": {
                        "icon": "",
                        "position": "top",
                        "content": ""
                    },
                    "before": "",
                    "after": "",
                    "class": "",
                    "sanitize_callback": "",
                    "save_field": true
                },
                "color_mdw3t0k0fpq": {
                    "_id": "color_mdw3t0k0fpq",
                    "_state": "collapsed",
                    "name": "Success",
                    "id": "success",
                    "type": "color",
                    "label_description": "",
                    "desc": "",
                    "std": "#28a745",
                    "alpha_channel": true,
                    "max_clone": "",
                    "add_button": "",
                    "admin_columns": {
                        "position": {
                            "type": "after",
                            "column": "title"
                        },
                        "title": "",
                        "before": "",
                        "after": ""
                    },
                    "columns": 2,
                    "tooltip": {
                        "icon": "",
                        "position": "top",
                        "content": ""
                    },
                    "before": "",
                    "after": "",
                    "class": "",
                    "sanitize_callback": "",
                    "save_field": true
                },
                "color_i7b5amblz7g": {
                    "_id": "color_i7b5amblz7g",
                    "_state": "collapsed",
                    "name": "Danger",
                    "id": "danger",
                    "type": "color",
                    "label_description": "",
                    "desc": "",
                    "std": "#dc3545",
                    "alpha_channel": true,
                    "max_clone": "",
                    "add_button": "",
                    "admin_columns": {
                        "position": {
                            "type": "after",
                            "column": "title"
                        },
                        "title": "",
                        "before": "",
                        "after": ""
                    },
                    "columns": 2,
                    "tooltip": {
                        "icon": "",
                        "position": "top",
                        "content": ""
                    },
                    "before": "",
                    "after": "",
                    "class": "",
                    "sanitize_callback": "",
                    "save_field": true
                },
                "color_zknmksal8kh": {
                    "_id": "color_zknmksal8kh",
                    "_state": "expanded",
                    "name": "Info",
                    "id": "info",
                    "type": "color",
                    "label_description": "",
                    "desc": "",
                    "std": "#17a2b8",
                    "alpha_channel": true,
                    "max_clone": "",
                    "add_button": "",
                    "admin_columns": {
                        "position": {
                            "type": "after",
                            "column": "title"
                        },
                        "title": "",
                        "before": "",
                        "after": ""
                    },
                    "columns": 2,
                    "tooltip": {
                        "icon": "",
                        "position": "top",
                        "content": ""
                    },
                    "before": "",
                    "after": "",
                    "class": "",
                    "sanitize_callback": "",
                    "save_field": true
                }
            }
        },
        "custom_html_b9qxes5pa2j": {
            "_id": "custom_html_b9qxes5pa2j",
            "_state": "expanded",
            "name": "",
            "id": "submit_button",
            "type": "custom_html",
            "label_description": "",
            "desc": "",
            "std": "<input type=\"submit\" name=\"submit\" id=\"submit\" class=\"btn ptn-primary\" value=\"Save Settings\"  />",
            "callback": "",
            "admin_columns": {
                "position": {
                    "type": "after",
                    "column": "title"
                },
                "title": "",
                "before": "",
                "after": ""
            },
            "columns": 6,
            "tooltip": {
                "icon": "",
                "position": "top",
                "content": ""
            },
            "before": "",
            "after": "",
            "class": "custom-submit",
            "sanitize_callback": "",
            "save_field": true
        }
    },
    "data": {
        "tab_index": 0
    },
    "meta_box": {
        "title": "Bootstrap Settings",
        "id": "bstg_settingfields_colors",
        "settings_pages": [
            "bstg_general_settings"
        ],
        "class": "bstg_settings",
        "text_domain": "hp",
        "function_name": "hp_register_settingColors",
        "fields": [
            {
                "id": "general_settings",
                "type": "group",
                "collapsible": true,
                "default_state": "collapsed",
                "save_state": true,
                "group_title": "General Settings",
                "class": "bstg_accordion_wrapper",
                "fields": [
                    {
                        "name": "Enqueue Bootstrap inside of Gutenberg?",
                        "id": "enqueue_bs_in_gb",
                        "type": "switch",
                        "style": "rounded",
                        "std": true
                    },
                    {
                        "name": "Where to enqueue Bootstraps' Javascript File",
                        "id": "enqueue_bs_js",
                        "type": "select_advanced",
                        "options": {
                            "backend": "Gutenberg",
                            "frontend": "Frontend"
                        },
                        "multiple": true,
                        "select_all_none": true,
                        "tooltip": {
                            "icon": "",
                            "position": "top",
                            "content": "bootstrap.min.js"
                        }
                    },
                    {
                        "name": "Where to enqueue Popper.js File",
                        "id": "enqueue_bs_popper",
                        "type": "select_advanced",
                        "options": {
                            "backend": "Gutenberg",
                            "frontend": "Frontend"
                        },
                        "multiple": true,
                        "select_all_none": true,
                        "tooltip": {
                            "icon": "",
                            "position": "top",
                            "content": "popper.min.js"
                        }
                    }
                ]
            },
            {
                "id": "components",
                "type": "group",
                "collapsible": true,
                "default_state": "collapsed",
                "save_state": true,
                "group_title": "Components",
                "class": "bstg_accordion_wrapper",
                "fields": [
                    {
                        "name": "Layout",
                        "id": "layout",
                        "type": "checkbox_list",
                        "options": {
                            "@import \"containers\";": "Container",
                            "@import \"grid\";": "Grids"
                        },
                        "inline": true,
                        "select_all_none": true,
                        "_callback": "components_layout"
                    },
                    {
                        "name": "Design",
                        "id": "design",
                        "type": "checkbox_list",
                        "options": {
                            "@import \"alert\";": "Alert",
                            "@import \"badge\";": "Badge",
                            "@import \"buttons\";": "Buttons",
                            "@import \"button-group\";": "Button-Groups",
                            "@import \"card\";": "Cards",
                            "@import \"close\";": "Close",
                            "@import \"dropdown\";": "Dropdown",
                            "@import \"forms\";": "Forms",
                            "@import \"images\";": "Images",
                            "@import \"list-group\";": "List-Group",
                            "@import \"nav\";": "Nav",
                            "@import \"navbar\";": "Navbar",
                            "@import \"pagination\";": "Pagination",
                            "@import \"placeholders\";": "Placeholders",
                            "@import \"popover\";": "Popover",
                            "@import \"progress\";": "Progress",
                            "@import \"spinners\";": "Spinners",
                            "@import \"tables\";": "Tables"
                        },
                        "inline": true,
                        "select_all_none": true,
                        "_callback": "components_design"
                    },
                    {
                        "name": "Functionality",
                        "id": "functionality",
                        "type": "checkbox_list",
                        "options": {
                            "@import \"accordion\";": "Accordion",
                            "@import \"carousel\";": "Carousel",
                            "@import \"modal\";": "Modal",
                            "@import \"offcanvas\";": "Offcanvas",
                            "@import \"popover\";": "Popover",
                            "@import \"toasts\";": "Toasts",
                            "@import \"tooltip\";": "Tooltip"
                        },
                        "inline": true,
                        "select_all_none": true,
                        "_callback": "components_functionality"
                    }
                ]
            },
            {
                "id": "colors",
                "type": "group",
                "collapsible": true,
                "default_state": "collapsed",
                "save_state": true,
                "group_title": "Colors",
                "class": "bstg_accordion_wrapper",
                "fields": [
                    {
                        "name": "Primary",
                        "id": "primary",
                        "type": "color",
                        "std": "#3f00b5",
                        "alpha_channel": true,
                        "columns": 2
                    },
                    {
                        "name": "Secondary",
                        "id": "secondary",
                        "type": "color",
                        "std": "#1f1f25",
                        "alpha_channel": true,
                        "columns": 2
                    },
                    {
                        "name": "White",
                        "id": "white",
                        "type": "color",
                        "std": "#FFFFFF",
                        "columns": 2,
                        "tooltip": {
                            "icon": "",
                            "position": "top",
                            "content": "Hauptsächlich für Texte auf dunkleren Hintergründen verwendet!"
                        }
                    },
                    {
                        "name": "Light",
                        "id": "light",
                        "type": "color",
                        "std": "#f8f9fa",
                        "alpha_channel": true,
                        "columns": 2,
                        "tooltip": {
                            "icon": "",
                            "position": "top",
                            "content": "Wird beispielsweise für hellere Hintergründe verwendet!"
                        }
                    },
                    {
                        "name": "Dark",
                        "id": "dark",
                        "type": "color",
                        "std": "#343a40",
                        "alpha_channel": true,
                        "columns": 2
                    },
                    {
                        "name": "Warning",
                        "id": "warning",
                        "type": "color",
                        "std": "#ffc107",
                        "alpha_channel": true,
                        "columns": 2
                    },
                    {
                        "name": "Success",
                        "id": "success",
                        "type": "color",
                        "std": "#28a745",
                        "alpha_channel": true,
                        "columns": 2
                    },
                    {
                        "name": "Danger",
                        "id": "danger",
                        "type": "color",
                        "std": "#dc3545",
                        "alpha_channel": true,
                        "columns": 2
                    },
                    {
                        "name": "Info",
                        "id": "info",
                        "type": "color",
                        "std": "#17a2b8",
                        "alpha_channel": true,
                        "columns": 2
                    }
                ]
            },
            {
                "id": "submit_button",
                "type": "custom_html",
                "std": "<input type=\"submit\" name=\"submit\" id=\"submit\" class=\"btn ptn-primary\" value=\"Save Settings\"  />",
                "columns": 6,
                "class": "custom-submit"
            }
        ]
    }
}